rshelly-0.5.data/scripts/rshelly
utils/__init__.py
utils/database.py
rshelly-0.5.dist-info/LICENSE
rshelly-0.5.dist-info/METADATA
rshelly-0.5.dist-info/WHEEL
rshelly-0.5.dist-info/top_level.txt
rshelly-0.5.dist-info/RECORD
